{"features": [{"type": "Feature", "_id": "3", "geometry": {"type": "Point", "coordinates": [21.00701, 52.2294]}, "properties": {"NAZWA_SERWIS": "Dworzec Warszawa Śródmieście", "Opis": "Dworzec Warszawa Śródmieście", "Adres": "Aleje Jerozolimskie 50", "Telefon/fax": "022 9436", "Liczba peronów": "3"}}, {"type": "Feature", "_id": "6", "geometry": {"type": "Point", "coordinates": [21.04434, 52.24612]}, "properties": {"NAZWA_SERWIS": "Dworzec Warszawa Stadion", "Opis": "Dworzec Warszawa Stadion", "Adres": "Zamoyskiego 1", "Telefon/fax": "022 9436", "Liczba peronów": "2"}}, {"type": "Feature", "_id": "7", "geometry": {"type": "Point", "coordinates": [21.02814, 52.23371]}, "properties": {"NAZWA_SERWIS": "Dworzec Warszawa Powiśle", "Opis": "Dworzec Warszawa Powiśle", "Adres": "Smolna 5", "Telefon/fax": "022 9436", "Liczba peronów": "2"}}, {"type": "Feature", "_id": "9", "geometry": {"type": "Point", "coordinates": [20.9901, 52.22561]}, "properties": {"NAZWA_SERWIS": "Dworzec Warszawa Ochota", "Opis": "Dworzec Warszawa Ochota", "Adres": "Aleje Jerozolimskie ", "Telefon/fax": " ", "Liczba peronów": "2"}}], "type": "FeatureCollection"}