{"features": [{"type": "Feature", "_id": "6", "geometry": {"type": "Point", "coordinates": [21.04434, 52.24612]}, "properties": {"NAZWA_SERWIS": "Dworzec Warszawa Stadion", "Opis": "Dworzec Warszawa Stadion", "Adres": "Zamoyskiego 1", "Telefon/fax": "022 9436", "Liczba peronów": "2"}}], "type": "FeatureCollection"}