{"features": [{"type": "Feature", "_id": "410", "geometry": {"type": "Point", "coordinates": [20.9937, 52.25266]}, "properties": {"NAZWA_SERWIS": "Boisko do hokeja na trawie", "Lokalizacja": "D. B. Meiselsa 1", "Dzielnica": "Śródmieście", "Zarządca obiektu": "Szkoła Podstawowa nr 32 z Oddziałami Integracyjnymi im. Małego Powstańca", "Jednostka nadzorująca": "Urząd Dzielnicy Śródmieście m.st. Warszawy", "Strona WWW": "https://sp32.waw.pl/kontakt/"}}, {"type": "Feature", "_id": "1486", "geometry": {"type": "Point", "coordinates": [21.04589, 52.27368]}, "properties": {"NAZWA_SERWIS": "Boisko do hokeja na trawie", "Lokalizacja": "Gościeradowska 18/20", "Dzielnica": "Targówek", "Zarządca obiektu": "Szkoła Podstawowa nr 28 im. Stefana Żeromskiego", "Jednostka nadzorująca": "Urząd Dzielnicy Targówek m.st. Warszawy"}}, {"type": "Feature", "_id": "1656", "geometry": {"type": "Point", "coordinates": [21.00715, 52.24243]}, "properties": {"NAZWA_SERWIS": "Boisko do hokeja na trawie", "Lokalizacja": "Niecała 14", "Dzielnica": "Śródmieście", "Zarządca obiektu": "Szkoła Podstawowa nr 75 im. Marii Konopnickiej", "Jednostka nadzorująca": "Urząd Dzielnicy Śródmieście m.st. Warszawy"}}, {"type": "Feature", "_id": "1963", "geometry": {"type": "Point", "coordinates": [20.92702, 52.25878]}, "properties": {"NAZWA_SERWIS": "Boisko wielozadaniowe", "Lokalizacja": "Oławska 3", "Dzielnica": "Bemowo", "Zarządca obiektu": "Szkoła Podstawowa z Oddziałami Integracyjnymi nr 341 im. Twórców Literatury Dziecięcej", "Jednostka nadzorująca": "Urząd Dzielnicy Bemowo m.st. Warszawy", "Strona WWW": "https://sp341.edupage.org/", "Części składowe boiska wielozadaniowego ": "Boisko do hokeja na trawie, Boisko do piłki siatkowej"}}, {"type": "Feature", "_id": "2356", "geometry": {"type": "Point", "coordinates": [21.05969, 52.23642]}, "properties": {"NAZWA_SERWIS": "Boisko do hokeja na trawie", "Lokalizacja": "Saska 78", "Dzielnica": "Praga-Południe", "Zarządca obiektu": "Zespół Szkół nr 21", "Jednostka nadzorująca": "Urząd Dzielnicy Praga-Południe m.st. Warszawy"}}], "type": "FeatureCollection"}